cast_action_plan/__init__.py
cast_action_plan/action_plan.py
cast_action_plan/config.py
cast_action_plan/main.py
cast_action_plan/rules.xlsx
com.castsoftware.uc.action_plan-1.0.1.dist-info/LICENSE
com.castsoftware.uc.action_plan-1.0.1.dist-info/METADATA
com.castsoftware.uc.action_plan-1.0.1.dist-info/WHEEL
com.castsoftware.uc.action_plan-1.0.1.dist-info/top_level.txt
com.castsoftware.uc.action_plan-1.0.1.dist-info/RECORD
