Metadata-Version: 2.1
Name: com.castsoftware.uc.action-plan
Version: 1.0.1
Summary: Generate an action plan for CAST Software rule violations
Home-page: https://github.com/CAST-Extend/com.castsoftware.uc.action-plan
Author: Nevin Kaplan
Author-email: n.kaplan@castsoftware.com
Project-URL: Homepage, https://github.com/CAST-Extend/com.castsoftware.uc.action-plan
Project-URL: Bug Tracker, https://github.com/pypa/sampleproject/issues
Classifier: Programming Language :: Python :: 3
Classifier: License :: OSI Approved :: GNU General Public License v3 (GPLv3)
Classifier: Operating System :: OS Independent
Requires-Python: >=3.10
License-File: LICENSE
Requires-Dist: com.castsoftware.uc.python.common
Requires-Dist: et-xmlfile
Requires-Dist: numpy
Requires-Dist: openpyxl
Requires-Dist: pandas
Requires-Dist: psycopg2
Requires-Dist: python-dateutil
Requires-Dist: pytz
Requires-Dist: six
